chess_corners-0.3.1.dist-info/METADATA
chess_corners-0.3.1.dist-info/WHEEL
chess_corners/__init__.py
chess_corners/chess_corners.pyd
chess_corners-0.3.1.dist-info/RECORD
