Metadata-Version: 2.4
Name: chess_corners
Version: 0.3.1
Classifier: Programming Language :: Python
Classifier: Programming Language :: Rust
Classifier: Operating System :: OS Independent
Summary: Python bindings for the fast ChESS chessboard corner detector (Rust backend)
Author: Vitaly Vorobyev
License: MIT
Requires-Python: >=3.10
Project-URL: Homepage, https://vitalyvorobyev.github.io/chess-corners-rs/
Project-URL: Source, https://github.com/VitalyVorobyev/chess-corners-rs
Project-URL: Issues, https://github.com/VitalyVorobyev/chess-corners-rs/issues
